maliapicall/__init__.py
maliapicall/muji.py
maliapicall/sk.py
maliapicall/wms.py
maliapicall-0.0.3.dist-info/licenses/LICENSE
maliapicall-0.0.3.dist-info/METADATA
maliapicall-0.0.3.dist-info/WHEEL
maliapicall-0.0.3.dist-info/top_level.txt
maliapicall-0.0.3.dist-info/RECORD
