Metadata-Version: 2.4
Name: maliapicall
Version: 0.0.3
Summary: A package to call Mali APIs
Author-email: senn117 <createforwoek@gmail.com>
Classifier: Programming Language :: Python :: 3
Classifier: License :: OSI Approved :: MIT License
Classifier: Operating System :: OS Independent
Requires-Python: >=3.7
License-File: LICENSE
Dynamic: license-file
